no_route/__init__.py
no_route/visitors.py
tests/__init__.py
no_route-0.0.0.dist-info/LICENSE
no_route-0.0.0.dist-info/METADATA
no_route-0.0.0.dist-info/WHEEL
no_route-0.0.0.dist-info/entry_points.txt
no_route-0.0.0.dist-info/top_level.txt
no_route-0.0.0.dist-info/RECORD
